binomial_cis/__init__.py
binomial_cis/binomial_helper.py
binomial_cis/conf_intervals.py
binomial_cis/mixed_monotonic.py
binomial_cis/plotting.py
binomial_cis/volume.py
binomial_cis-0.0.12.dist-info/licenses/LICENSE
binomial_cis-0.0.12.dist-info/METADATA
binomial_cis-0.0.12.dist-info/WHEEL
binomial_cis-0.0.12.dist-info/top_level.txt
binomial_cis-0.0.12.dist-info/RECORD
